graphql_http/__init__.py
graphql_http/error.py
graphql_http/helpers.py
graphql_http/introspection.py
graphql_http/server.py
graphql_http/graphiql/index.html
graphql_http-2.2.6.dist-info/licenses/LICENSE
graphql_http-2.2.6.dist-info/METADATA
graphql_http-2.2.6.dist-info/WHEEL
graphql_http-2.2.6.dist-info/top_level.txt
graphql_http-2.2.6.dist-info/RECORD
