Metadata-Version: 2.4
Name: graphql-http
Version: 2.2.6
Summary: HTTP Server for GraphQL.
Author-email: Robert Parker <rob@parob.com>
License: MIT
Project-URL: Homepage, https://gitlab.com/parob/graphql-http
Project-URL: Repository, https://gitlab.com/parob/graphql-http
Keywords: GraphQL,HTTP,Server,starlette
Classifier: Development Status :: 3 - Alpha
Classifier: Intended Audience :: Developers
Classifier: Programming Language :: Python :: 3
Classifier: License :: OSI Approved :: MIT License
Classifier: Operating System :: OS Independent
Requires-Python: <3.13,>=3.11
License-File: LICENSE
Requires-Dist: graphql-core
Requires-Dist: graphql-api
Requires-Dist: packaging
Requires-Dist: graphql-schema-diff
Requires-Dist: pyjwt[crypto]
Requires-Dist: starlette
Requires-Dist: uvicorn
Requires-Dist: python-multipart
Requires-Dist: httpx
Dynamic: license-file
